tkcustomessagebox/__init__.py
tkcustomessagebox/pythoncustomsgbox.py
tkcustomessagebox-2025.7.9.dist-info/licenses/LICENSE
tkcustomessagebox-2025.7.9.dist-info/METADATA
tkcustomessagebox-2025.7.9.dist-info/WHEEL
tkcustomessagebox-2025.7.9.dist-info/top_level.txt
tkcustomessagebox-2025.7.9.dist-info/RECORD
