Metadata-Version: 2.4
Name: tkcustomessagebox
Version: 2025.7.9
Summary: A Python package has a custom messagebox using Customtkinter and the Fredoka One font.
License-Expression: MIT
Classifier: Programming Language :: Python :: 3
Classifier: Operating System :: OS Independent
Requires-Python: >=3.10
License-File: LICENSE
Requires-Dist: customtkinter
Dynamic: license-file
